alnfile/__init__.py
alnfile/df_utils.py
alnfile/imod_utils.py
alnfile/io.py
alnfile/py.typed
alnfile/data_model/__init__.py
alnfile/data_model/aln_data.py
alnfile/data_model/dark_frames.py
alnfile/data_model/global_alignments.py
alnfile/data_model/local_alignments.py
alnfile-0.1.1.dist-info/METADATA
alnfile-0.1.1.dist-info/WHEEL
alnfile-0.1.1.dist-info/licenses/LICENSE
alnfile-0.1.1.dist-info/RECORD
