Metadata-Version: 2.4
Name: alnfile
Version: 0.1.1
Summary: A Python package for reading AreTomo alignment files into pandas DataFrames.
Project-URL: homepage, https://github.com/teamtomo/alnfile
Project-URL: repository, https://github.com/teamtomo/alnfile
Project-URL: documentation, https://github.com/teamtomo/alnfile#readme
Project-URL: changelog, https://github.com/teamtomo/alnfile#changelog
Project-URL: Bug Tracker, https://github.com/teamtomo/alnfile/issues
Project-URL: Source Code, https://github.com/teamtomo/alnfile
Author-email: Davide Torre <davidetorre99@gmail.com>
License: BSD-3-Clause
License-File: LICENSE
Classifier: Development Status :: 4 - Beta
Classifier: Intended Audience :: Science/Research
Classifier: License :: OSI Approved :: BSD License
Classifier: Programming Language :: Python :: 3
Classifier: Programming Language :: Python :: 3.10
Classifier: Programming Language :: Python :: 3.11
Classifier: Programming Language :: Python :: 3.12
Classifier: Programming Language :: Python :: 3.13
Classifier: Typing :: Typed
Requires-Python: >=3.10
Requires-Dist: pandas>=1.5.0
Requires-Dist: pydantic>=2.0.0
